fuzzychinese/__init__.py
fuzzychinese/_character_to_radical.py
fuzzychinese/_character_to_stroke.py
fuzzychinese/_fuzzy_chinese_match.py
fuzzychinese/_utils.py
fuzzychinese/dict_chinese_radical.txt
fuzzychinese/dict_chinese_stroke.txt
fuzzychinese-0.1.5.dist-info/LICENSE
fuzzychinese-0.1.5.dist-info/METADATA
fuzzychinese-0.1.5.dist-info/WHEEL
fuzzychinese-0.1.5.dist-info/top_level.txt
fuzzychinese-0.1.5.dist-info/RECORD
