Metadata-Version: 2.1
Name: fuzzychinese
Version: 0.1.5
Summary: A small package to fuzzy match chinese words 中文模糊匹配
Home-page: https://github.com/znwang25/fuzzychinese
Author: znwang25
Author-email: znwang25@gmail.com
License: UNKNOWN
Keywords: NLP,fuzzy matching,Chinese word
Platform: UNKNOWN
Classifier: Intended Audience :: Developers
Classifier: Programming Language :: Python :: 3
Classifier: License :: OSI Approved :: BSD License
Classifier: Operating System :: OS Independent
Classifier: Natural Language :: Chinese (Simplified)
Classifier: Natural Language :: Chinese (Traditional)
Classifier: Topic :: Text Processing :: Linguistic
Classifier: Topic :: Text Processing
